deskA/__init__.py
deskA/main.py
deskA-0.0.1.dist-info/METADATA
deskA-0.0.1.dist-info/WHEEL
deskA-0.0.1.dist-info/top_level.txt
deskA-0.0.1.dist-info/RECORD
