Metadata-Version: 2.1
Name: deskA
Version: 0.0.1
Summary: A package to help with making desktop assistants.
Home-page: UNKNOWN
Author: Blinken77YT
Author-email: <mail@neuralnine.com>
License: UNKNOWN
Keywords: python,video,stream,video stream,camera stream,sockets
Platform: UNKNOWN
Classifier: Development Status :: 1 - Planning
Classifier: Intended Audience :: Developers
Classifier: Programming Language :: Python :: 3
Classifier: Operating System :: Unix
Classifier: Operating System :: MacOS :: MacOS X
Classifier: Operating System :: Microsoft :: Windows
Requires-Dist: gtts
Requires-Dist: speech-recognition
Requires-Dist: subprocess
Requires-Dist: pyaudio
Requires-Dist: os
Requires-Dist: datetime
